niolithic/__init__.py
niolithic/client.py
niolithic-0.1.0.dist-info/LICENSE
niolithic-0.1.0.dist-info/WHEEL
niolithic-0.1.0.dist-info/METADATA
niolithic-0.1.0.dist-info/RECORD
