Metadata-Version: 2.1
Name: niolithic
Version: 0.1.0
Summary: A simple Matrix client library wrapped around `matrix-nio`
Home-page: https://gitlab.com/deepadmax/niolithic
License: MIT
Author: Maximillian Strand
Author-email: maximillian.strand@protonmail.com
Requires-Python: >=3.10,<4.0
Classifier: License :: OSI Approved :: MIT License
Classifier: Programming Language :: Python :: 3
Classifier: Programming Language :: Python :: 3.10
Requires-Dist: Markdown (>=3.3.7,<4.0.0)
Requires-Dist: matrix-nio[e2e] (>=0.19.0,<0.20.0)
Requires-Dist: rich (>=12.3.0,<13.0.0)
